[
    {
        "key": "dbln",
        "value": "%7B%22100057567365751%22%3A%22QpqPJKYx%22%7D",
        "domain": "facebook.com",
        "path": "/login/device-based/",
        "hostOnly": false,
        "creation": "2024-04-22T03:48:07.093Z",
        "lastAccessed": "2024-04-22T03:48:07.093Z"
    },
    {
        "key": "datr",
        "value": "k9UjZtPIXKLNcJNfB7HylvO5",
        "domain": "facebook.com",
        "path": "/",
        "hostOnly": false,
        "creation": "2024-04-22T03:48:07.093Z",
        "lastAccessed": "2024-04-22T03:48:07.093Z"
    },
    {
        "key": "sb",
        "value": "k9UjZri8sXiAmbVreKiA60zw",
        "domain": "facebook.com",
        "path": "/",
        "hostOnly": false,
        "creation": "2024-04-22T03:48:07.093Z",
        "lastAccessed": "2024-04-22T03:48:07.093Z"
    },
    {
        "key": "ps_n",
        "value": "1",
        "domain": "facebook.com",
        "path": "/",
        "hostOnly": false,
        "creation": "2024-04-22T03:48:07.093Z",
        "lastAccessed": "2024-04-22T03:48:07.093Z"
    },
    {
        "key": "ps_l",
        "value": "1",
        "domain": "facebook.com",
        "path": "/",
        "hostOnly": false,
        "creation": "2024-04-22T03:48:07.093Z",
        "lastAccessed": "2024-04-22T03:48:07.093Z"
    },
    {
        "key": "locale",
        "value": "en_GB",
        "domain": "facebook.com",
        "path": "/",
        "hostOnly": false,
        "creation": "2024-04-22T03:48:07.093Z",
        "lastAccessed": "2024-04-22T03:48:07.093Z"
    },
    {
        "key": "vpd",
        "value": "v1%3B708x360x3",
        "domain": "facebook.com",
        "path": "/",
        "hostOnly": false,
        "creation": "2024-04-22T03:48:07.093Z",
        "lastAccessed": "2024-04-22T03:48:07.093Z"
    },
    {
        "key": "m_pixel_ratio",
        "value": "3",
        "domain": "facebook.com",
        "path": "/",
        "hostOnly": false,
        "creation": "2024-04-22T03:48:07.093Z",
        "lastAccessed": "2024-04-22T03:48:07.093Z"
    },
    {
        "key": "c_user",
        "value": "100057567365751",
        "domain": "facebook.com",
        "path": "/",
        "hostOnly": false,
        "creation": "2024-04-22T03:48:07.093Z",
        "lastAccessed": "2024-04-22T03:48:07.093Z"
    },
    {
        "key": "xs",
        "value": "4%3AW2UZB47uOpkSGA%3A2%3A1713757647%3A-1%3A5903",
        "domain": "facebook.com",
        "path": "/",
        "hostOnly": false,
        "creation": "2024-04-22T03:48:07.093Z",
        "lastAccessed": "2024-04-22T03:48:07.093Z"
    },
    {
        "key": "fr",
        "value": "02jgHYYFQd37ArpEf.AWVshGaLwVaMBDYZzbNQzE8BSfI.BmI9WT..AAA.0.0.BmJd3P.AWVxxIuPL7I",
        "domain": "facebook.com",
        "path": "/",
        "hostOnly": false,
        "creation": "2024-04-22T03:48:07.093Z",
        "lastAccessed": "2024-04-22T03:48:07.093Z"
    },
    {
        "key": "m_page_voice",
        "value": "100057567365751",
        "domain": "facebook.com",
        "path": "/",
        "hostOnly": false,
        "creation": "2024-04-22T03:48:07.093Z",
        "lastAccessed": "2024-04-22T03:48:07.093Z"
    },
    {
        "key": "wd",
        "value": "360x708",
        "domain": "facebook.com",
        "path": "/",
        "hostOnly": false,
        "creation": "2024-04-22T03:48:07.093Z",
        "lastAccessed": "2024-04-22T03:48:07.093Z"
    },
    {
        "key": "fbl_st",
        "value": "100722994%3BT%3A28562627",
        "domain": "facebook.com",
        "path": "/",
        "hostOnly": false,
        "creation": "2024-04-22T03:48:07.093Z",
        "lastAccessed": "2024-04-22T03:48:07.093Z"
    },
    {
        "key": "wl_cbv",
        "value": "v2%3Bclient_version%3A2472%3Btimestamp%3A1713757650",
        "domain": "facebook.com",
        "path": "/",
        "hostOnly": false,
        "creation": "2024-04-22T03:48:07.093Z",
        "lastAccessed": "2024-04-22T03:48:07.093Z"
    }
]
